[{"name": "Milk", "longlat": ["-122.420105", "37.783802"]}, {"name": "Mckinley Elementary School", "longlat": ["-122.436279", "37.766884"]}, {"name": "Jewish Community Center San Francisco - Rosenberg Early Childhood Center", "longlat": ["-122.459488", "37.784588"]}, {"name": "Eureka Learning Center", "longlat": ["-122.437004", "37.754967"]}, {"name": "Noriega Early Education School", "longlat": ["-122.503654", "37.753834"]}, {"name": "Marin Preparatory School", "longlat": ["-122.436798", "37.760124"]}, {"name": "Montessori House Of Children", "longlat": ["-122.423416", "37.785046"]}, {"name": "West Portal Lutheran School", "longlat": ["-122.473999", "37.735092"]}, {"name": "Economic Opportunity Council Sf - Delta Preschool", "longlat": ["-122.409553", "37.713379"]}, {"name": "Teaching Tots Preschool", "longlat": ["-122.407471", "37.797092"]}, {"name": "Sutro Elementary / Early Education", "longlat": ["-122.471451", "37.783604"]}, {"name": "Marshall", "longlat": ["-122.401649", "37.736309"]}, {"name": "Francisco Middle School", "longlat": ["-122.410965", "37.804569"]}, {"name": "Star Of The Sea School", "longlat": ["-122.467285", "37.781563"]}, {"name": "San Francisco University High School", "longlat": ["-122.445351", "37.790657"]}, {"name": "Argonne Early Education School", "longlat": ["-122.47406", "37.773968"]}, {"name": "Flynn", "longlat": ["-122.411964", "37.747746"]}, {"name": "Hamlin School", "longlat": ["-122.432495", "37.7948"]}, {"name": "Little Star Preschool Too", "longlat": ["-122.47757", "37.748341"]}, {"name": "Sweet Peas Preschool - West", "longlat": ["-122.444008", "37.733597"]}, {"name": "Cross Cultural Family Center - Marcus Garvey Center", "longlat": ["-122.43486", "37.781597"]}, {"name": "Saint Peters School", "longlat": ["-122.410362", "37.751701"]}, {"name": "Saint Monica School", "longlat": ["-122.483337", "37.780613"]}, {"name": "City College of San Francisco John Adams Center", "longlat": ["-122.447189", "37.774086"]}, {"name": "Bright Horizons - Letterman Digital Arts Child Care Center", "longlat": ["-122.4505", "37.799175"]}, {"name": "West Portal Elementary School", "longlat": ["-122.464348", "37.742874"]}, {"name": "Lau", "longlat": ["-122.408806", "37.794399"]}, {"name": "Saint Ignatius College Preparatory", "longlat": ["-122.495819", "37.748863"]}, {"name": "Economic Opportunity Council Sf - Western Addition Childcare", "longlat": ["-122.434433", "37.778938"]}, {"name": "Haight Ashbury Community Nursery School", "longlat": ["-122.451889", "37.762451"]}, {"name": "Convent Of The Sacred Heart Elementary School", "longlat": ["-122.433876", "37.794689"]}, {"name": "Hilltop Child Development Center", "longlat": ["-122.409149", "37.750465"]}, {"name": "Visitacion Valley Middle School", "longlat": ["-122.412079", "37.715744"]}, {"name": "Bryant Early Education / Bryant Elementary", "longlat": ["-122.404694", "37.751453"]}, {"name": "Giannini", "longlat": ["-122.496666", "37.750301"]}, {"name": "Economic Opportunity Council Sf - Martin Luther King Childcare", "longlat": ["-122.386047", "37.737042"]}, {"name": "Malcolm X Elementary School", "longlat": ["-122.380966", "37.734238"]}, {"name": "Sheridan Elementary School / Preschool", "longlat": ["-122.459633", "37.714478"]}, {"name": "Hearst", "longlat": ["-122.500053", "37.74363"]}, {"name": "Wu Yee Child Development Center - Potrero Hill", "longlat": ["-122.400314", "37.758236"]}, {"name": "Hilltop High Special Services Center", "longlat": ["-122.40963", "37.750454"]}, {"name": "Kai Ming Head Start - North Beach Center", "longlat": ["-122.41642", "37.804852"]}, {"name": "Marin Day School - Congregation Sherith Israel", "longlat": ["-122.438248", "37.788647"]}, {"name": "Carmichael", "longlat": ["-122.40049", "37.78056"]}, {"name": "Marin Day School - Spear St", "longlat": ["-122.392525", "37.790878"]}, {"name": "Mission Neighborhood Centers - Alemany Head Start", "longlat": ["-122.417885", "37.733013"]}, {"name": "Jefferson Elementary School", "longlat": ["-122.47673", "37.763065"]}, {"name": "Fusion Academy San Francisco", "longlat": ["-122.404182", "37.797028"]}, {"name": "Argonne Elementary School", "longlat": ["-122.476311", "37.775307"]}, {"name": "Little Angels Japanese Preschool", "longlat": ["-122.466431", "37.761131"]}, {"name": "Bright Horizons - Pacific Gas And Electric", "longlat": ["-122.395592", "37.791763"]}, {"name": "Moscone", "longlat": ["-122.41262", "37.756741"]}, {"name": "Sherman Elementary School", "longlat": ["-122.426117", "37.797802"]}, {"name": "Kipp Bayview Academy", "longlat": ["-122.396561", "37.719532"]}, {"name": "Sweet Peas Preschool - East", "longlat": ["-122.411102", "37.764515"]}, {"name": "Edgewood Center For Children And Families", "longlat": ["-122.486259", "37.737984"]}, {"name": "Wen Jian Ying", "longlat": ["-122.447571", "37.72802"]}, {"name": "Lawton Alternative School", "longlat": ["-122.489098", "37.758049"]}, {"name": "Chinese American International School", "longlat": ["-122.424232", "37.772228"]}, {"name": "Faces Sf Child Development Program - Bayview-Hunters Point", "longlat": ["-122.384216", "37.734039"]}, {"name": "Visitacion Valley Elementary School", "longlat": ["-122.409897", "37.712524"]}, {"name": "Little Star Preschool", "longlat": ["-122.493668", "37.742508"]}, {"name": "New Traditions Elementary School", "longlat": ["-122.450264", "37.773884"]}, {"name": "San Francisco County Civic Center Secondary School", "longlat": ["-122.422943", "37.780296"]}, {"name": "Saint Pauls School", "longlat": ["-122.426926", "37.743923"]}, {"name": "Rooftop (K-4 Burnett Campus)", "longlat": ["-122.443222", "37.75481"]}, {"name": "Saints Peter And Paul Elementary School", "longlat": ["-122.410217", "37.801598"]}, {"name": "Centro Las Olas - Centro De Desarrollo Infantil", "longlat": ["-122.424049", "37.748364"]}, {"name": "Cornerstone Academy", "longlat": ["-122.418327", "37.729584"]}, {"name": "Claire Lilienthal Alternative School - Madison Campus", "longlat": ["-122.458076", "37.78722"]}, {"name": "Childrens After School Arts", "longlat": ["-122.435242", "37.75959"]}, {"name": "Congregation Beth Sholom Family Preschool", "longlat": ["-122.473381", "37.782387"]}, {"name": "Parker", "longlat": ["-122.411041", "37.797619"]}, {"name": "Happy Day Preschool", "longlat": ["-122.474892", "37.742836"]}, {"name": "Spring Valley Elementary / Early Education", "longlat": ["-122.418816", "37.794006"]}, {"name": "Mission Neighborhood Centers - 24Th St Head Start", "longlat": ["-122.412224", "37.752457"]}, {"name": "Yick Wo Elementary School", "longlat": ["-122.416611", "37.80196"]}, {"name": "Russian Hill School", "longlat": ["-122.440193", "37.788521"]}, {"name": "San Francisco Public Montessori", "longlat": ["-122.433601", "37.792866"]}, {"name": "Hergl School", "longlat": ["-122.42572", "37.800377"]}, {"name": "Friends Of Saint Francis Child Care Center", "longlat": ["-122.430344", "37.768589"]}, {"name": "Chin", "longlat": ["-122.403221", "37.798611"]}, {"name": "Valdivia Family Day Care", "longlat": ["-122.406807", "37.752579"]}, {"name": "Cornerstone Academy", "longlat": ["-122.416847", "37.724953"]}, {"name": "Sanchez Elementary School  / Preschool", "longlat": ["-122.430359", "37.763454"]}, {"name": "Nihonmachi Little Friends - Sutter St", "longlat": ["-122.430557", "37.786717"]}, {"name": "Stuart Hall For Boys", "longlat": ["-122.434288", "37.794617"]}, {"name": "Bais Menachem Yeshiva Day School", "longlat": ["-122.487152", "37.773613"]}, {"name": "Little Angels Daycare", "longlat": ["-122.466423", "37.726673"]}, {"name": "Amici World School", "longlat": ["-122.445717", "37.803875"]}, {"name": "Burton", "longlat": ["-122.406555", "37.721546"]}, {"name": "City College of San Francisco Civic Center", "longlat": ["-122.414299", "37.779545"]}, {"name": "Washington", "longlat": ["-122.491013", "37.777905"]}, {"name": "Big City Montessori School", "longlat": ["-122.405312", "37.738655"]}, {"name": "Buena Vista / Horace Mann", "longlat": ["-122.420181", "37.753033"]}, {"name": "Alta Plaza Preschool", "longlat": ["-122.437195", "37.790203"]}, {"name": "Glenridge Cooperative Nursery School", "longlat": ["-122.440033", "37.736191"]}, {"name": "Guadalupe Elementary School", "longlat": ["-122.434029", "37.710182"]}, {"name": "Telegraph Hill Neighborhood Center Child Development Preschool", "longlat": ["-122.412537", "37.803444"]}, {"name": "Cobb", "longlat": ["-122.439552", "37.787678"]}, {"name": "Alamo Elementary School", "longlat": ["-122.4823", "37.783005"]}, {"name": "Pacific Primary - Yellow Sun School", "longlat": ["-122.441734", "37.775658"]}, {"name": "Stockton", "longlat": ["-122.40908", "37.795082"]}, {"name": "Kai Ming Head Start - Sunset Center", "longlat": ["-122.496277", "37.742394"]}, {"name": "Kai Ming Head Start - Tkl Center (Dr T Kong Lee)", "longlat": ["-122.409294", "37.79372"]}, {"name": "Glen Park Elementary School", "longlat": ["-122.435623", "37.733131"]}, {"name": "Economic Opportunity Council Sf - Sojourner Truth Childcare", "longlat": ["-122.381874", "37.735832"]}, {"name": "Stevenson", "longlat": ["-122.49276", "37.748844"]}, {"name": "Bright Horizons - Kansas St", "longlat": ["-122.404213", "37.766731"]}, {"name": "Taylor", "longlat": ["-122.40731", "37.727329"]}, {"name": "Second Community Child Care Center", "longlat": ["-122.456131", "37.753712"]}, {"name": "Ortega", "longlat": ["-122.466675", "37.716782"]}, {"name": "Redding Elementary / Early Education", "longlat": ["-122.41925", "37.78952"]}, {"name": "Scandanavian School", "longlat": ["-122.457878", "37.746582"]}, {"name": "Wind In The Willows Early Learning Center", "longlat": ["-122.451462", "37.731258"]}, {"name": "Telegraph Hill Parent Participation Nursery School", "longlat": ["-122.410377", "37.795681"]}, {"name": "Rocky Mountain Participation Nursery School", "longlat": ["-122.471603", "37.74184"]}, {"name": "Moldovan Academy", "longlat": ["-122.42968", "37.748898"]}, {"name": "Ucsf - Parnassus-Kirkham Child Development Center", "longlat": ["-122.461166", "37.761524"]}, {"name": "Saint Nicholas Day Care And Preschool", "longlat": ["-122.440422", "37.744923"]}, {"name": "International Studies Academy", "longlat": ["-122.400688", "37.761704"]}, {"name": "Everett Middle School", "longlat": ["-122.429367", "37.763577"]}, {"name": "My Little Learning Tree", "longlat": ["-122.482086", "37.782394"]}, {"name": "San Francisco Waldorf High School", "longlat": ["-122.471199", "37.736015"]}, {"name": "Family School", "longlat": ["-122.418137", "37.747994"]}, {"name": "Mission Neighborhood Centers - Edificio De Mujeres / Womens Building", "longlat": ["-122.422615", "37.761421"]}, {"name": "Adda Clevenger School", "longlat": ["-122.424461", "37.753738"]}, {"name": "Faces Sf Child Development Program - Hayes Valley", "longlat": ["-122.428032", "37.772907"]}, {"name": "Walden Academy", "longlat": ["-122.426147", "37.772942"]}, {"name": "San Francisco Expeditionary School", "longlat": ["-122.445892", "37.793186"]}, {"name": "Little Childrens Developmental Center", "longlat": ["-122.431045", "37.781956"]}, {"name": "Montessori Childrens Center", "longlat": ["-122.480911", "37.718266"]}, {"name": "Carmichael", "longlat": ["-122.406456", "37.776382"]}, {"name": "Holy Family Day Home", "longlat": ["-122.425796", "37.764992"]}, {"name": "Saint Gabriel Catholic School", "longlat": ["-122.498634", "37.739563"]}, {"name": "Lincoln", "longlat": ["-122.48024", "37.746594"]}, {"name": "Love And Learn Nursery School", "longlat": ["-122.414795", "37.77335"]}, {"name": "Havard", "longlat": ["-122.388588", "37.734085"]}, {"name": "City College of San Francisco Fort Mason Site", "longlat": ["-122.431824", "37.80677"]}, {"name": "Chinatown Community Childrens Center", "longlat": ["-122.409103", "37.79361"]}, {"name": "Balboa Preschool", "longlat": ["-122.464477", "37.776932"]}, {"name": "Marina Childrens Center", "longlat": ["-122.431488", "37.800774"]}, {"name": "Rodriguez", "longlat": ["-122.418556", "37.749821"]}, {"name": "Kai Ming Head Start - Geary Center", "longlat": ["-122.486191", "37.77972"]}, {"name": "King", "longlat": ["-122.405807", "37.727741"]}, {"name": "San Francisco Christian School", "longlat": ["-122.447754", "37.710037"]}, {"name": "Cross Cultural Family Center - Bertha E Flemming Center", "longlat": ["-122.436233", "37.782711"]}, {"name": "Little Bear School", "longlat": ["-122.438095", "37.723179"]}, {"name": "Everyday Magic Child Development Center", "longlat": ["-122.485817", "37.730572"]}, {"name": "Alta Vista School", "longlat": ["-122.407196", "37.726391"]}, {"name": "Golden Bridges School", "longlat": ["-122.42231", "37.755467"]}, {"name": "Creative Arts Charter School", "longlat": ["-122.436073", "37.779804"]}, {"name": "Laurel Hill Nursery School", "longlat": ["-122.452728", "37.783798"]}, {"name": "Phoebe A Hearst Learning Center", "longlat": ["-122.427948", "37.782681"]}, {"name": "Marin Day School - Market Street", "longlat": ["-122.417358", "37.777226"]}, {"name": "Treasure Island Child Development Center", "longlat": ["-122.372505", "37.825985"]}, {"name": "Saint Anthony - Immaculate Conception School", "longlat": ["-122.414223", "37.747536"]}, {"name": "Starlight Christian Preschool 2", "longlat": ["-122.500977", "37.738022"]}, {"name": "Webster", "longlat": ["-122.400772", "37.762009"]}, {"name": "Oakes Childrens Center", "longlat": ["-122.412697", "37.74593"]}, {"name": "Sunset Cooperative Nursery School", "longlat": ["-122.508499", "37.756386"]}, {"name": "Laurel School", "longlat": ["-122.467331", "37.781941"]}, {"name": "Wu Yee Child Development Center - Westside", "longlat": ["-122.442268", "37.784466"]}, {"name": "De Marillac Academy", "longlat": ["-122.413345", "37.781658"]}, {"name": "San Francisco Waldorf School", "longlat": ["-122.44191", "37.790783"]}, {"name": "Ecole Notre Dame Des Victoires", "longlat": ["-122.406464", "37.791115"]}, {"name": "Grattan Elementary / Early Education", "longlat": ["-122.450424", "37.763493"]}, {"name": "Hoover", "longlat": ["-122.468964", "37.745556"]}, {"name": "Chibi Chan Preschool", "longlat": ["-122.429291", "37.788784"]}, {"name": "Presidio Hill School", "longlat": ["-122.456062", "37.788582"]}, {"name": "Hearing & Speech Center Of Northern California", "longlat": ["-122.438728", "37.781174"]}, {"name": "Starlight Christian Preschool 1", "longlat": ["-122.484924", "37.775311"]}, {"name": "Mission Neighborhood Centers - Valencia Gardens", "longlat": ["-122.423202", "37.767098"]}, {"name": "Lakeshore Elementary School", "longlat": ["-122.48542", "37.730324"]}, {"name": "Life Learning Academy Charter School", "longlat": ["-122.367996", "37.825512"]}, {"name": "German International School Of Silicon Valley - San Francisco Campus", "longlat": ["-122.455566", "37.800007"]}, {"name": "Marina Middle School", "longlat": ["-122.435478", "37.801827"]}, {"name": "San Francisco Schoolhouse (Congregation Beth Shalom)", "longlat": ["-122.473167", "37.782391"]}, {"name": "San Francisco City Academy", "longlat": ["-122.412201", "37.783505"]}, {"name": "Saint Brendan School", "longlat": ["-122.455925", "37.742855"]}, {"name": "Saint Finn Barr Catholic School", "longlat": ["-122.447411", "37.730446"]}, {"name": "Wu Yee Child Development Center - Lok Yuen", "longlat": ["-122.407791", "37.794365"]}, {"name": "Kai Ming Head Start - Battery Center", "longlat": ["-122.400581", "37.798973"]}, {"name": "City College of San Francisco Southeast Center", "longlat": ["-122.394096", "37.737148"]}, {"name": "Saint Marys School", "longlat": ["-122.404907", "37.795944"]}, {"name": "Rainbow Montessori Of San Francisco", "longlat": ["-122.480759", "37.743538"]}, {"name": "Sand Paths Academy", "longlat": ["-122.416717", "37.753468"]}, {"name": "Synergy Elementary School", "longlat": ["-122.420326", "37.750885"]}, {"name": "Lycee Francais De San Francisco", "longlat": ["-122.446968", "37.767971"]}, {"name": "Clarendon Elementary School", "longlat": ["-122.456268", "37.753754"]}, {"name": "Lycee Francais De San Francisco", "longlat": ["-122.476829", "37.751988"]}, {"name": "Katherine Delmar Burke School", "longlat": ["-122.493324", "37.784283"]}, {"name": "Marin Day School - San Francisco City Hall", "longlat": ["-122.418816", "37.779324"]}, {"name": "Mccoppin", "longlat": ["-122.464477", "37.77631"]}, {"name": "Gateway High School / Kipp Sf Bay Academy", "longlat": ["-122.436691", "37.783264"]}, {"name": "Galileo High School", "longlat": ["-122.424149", "37.803791"]}, {"name": "Kangaroos Preschool", "longlat": ["-122.441833", "37.731812"]}, {"name": "Glide Family Youth And Childcare Center", "longlat": ["-122.411697", "37.78529"]}, {"name": "Jefferson Early Education School", "longlat": ["-122.483162", "37.76236"]}, {"name": "Noe Valley Nursery School", "longlat": ["-122.440552", "37.743469"]}, {"name": "Ucsf - University Child Care Center - Laurel Heights", "longlat": ["-122.448387", "37.786099"]}, {"name": "Montessori Childrens House Of The West Coast", "longlat": ["-122.459686", "37.786671"]}, {"name": "Five Keys Charter", "longlat": ["-122.402229", "37.777107"]}, {"name": "Little Sunshine Childcare", "longlat": ["-122.46096", "37.7239"]}, {"name": "Saint Pauls Littlest Angel Preparatory", "longlat": ["-122.427742", "37.74419"]}, {"name": "City College of San Francisco Mission Center", "longlat": ["-122.420616", "37.754791"]}, {"name": "Economic Opportunity Council Sf - Oscaryne Williams Center Of Hope", "longlat": ["-122.394974", "37.755798"]}, {"name": "Alt School - Fort Mason", "longlat": ["-122.433907", "37.804562"]}, {"name": "Sloat", "longlat": ["-122.470482", "37.731258"]}, {"name": "Ark Christian Preschool", "longlat": ["-122.500786", "37.73803"]}, {"name": "Economic Opportunity Council Sf - Rainbow Preschool", "longlat": ["-122.407638", "37.796528"]}, {"name": "Laguna Golden Gate Child Care Center", "longlat": ["-122.42733", "37.780636"]}, {"name": "Playmates Cooperative Nursery School", "longlat": ["-122.500076", "37.743015"]}, {"name": "Miraloma Cooperative Nursery School", "longlat": ["-122.449142", "37.732193"]}, {"name": "Jewish Community Center San Francisco - Helen Diller Family Preschool", "longlat": ["-122.44722", "37.787365"]}, {"name": "Saint Stephen School", "longlat": ["-122.477684", "37.730911"]}, {"name": "Peters Place Nursery School", "longlat": ["-122.461357", "37.777092"]}, {"name": "Wu Yee Child Development Center - Chinatown Little Sprouts", "longlat": ["-122.410713", "37.797012"]}, {"name": "Milk", "longlat": ["-122.436447", "37.758926"]}, {"name": "Balboa High School", "longlat": ["-122.441399", "37.721142"]}, {"name": "Urban School Of San Francisco", "longlat": ["-122.44635", "37.770832"]}, {"name": "Mission Neighborhood Centers - Stevenson", "longlat": ["-122.421883", "37.771469"]}, {"name": "Serra", "longlat": ["-122.421486", "37.736912"]}, {"name": "Kids By The Bay Preschool", "longlat": ["-122.412102", "37.779549"]}, {"name": "Kinderhaus - German International Preschool", "longlat": ["-122.402496", "37.732529"]}, {"name": "Brandeis Hillel School Of San Francisco", "longlat": ["-122.475639", "37.713421"]}, {"name": "La Scuola International School", "longlat": ["-122.430046", "37.774921"]}, {"name": "Claire Lilienthal Alternative School - Scott Campus", "longlat": ["-122.442665", "37.803036"]}, {"name": "Kai Ming Head Start - Richmond Center", "longlat": ["-122.493202", "37.781128"]}, {"name": "Mission Education Center Elementary School", "longlat": ["-122.431435", "37.742203"]}, {"name": "Angelas Children Center", "longlat": ["-122.465179", "37.773998"]}, {"name": "Peabody", "longlat": ["-122.465027", "37.783855"]}, {"name": "Hillcrest Elementary School", "longlat": ["-122.418686", "37.728413"]}, {"name": "La Piccola Scuola Italiana Preschool", "longlat": ["-122.389198", "37.760681"]}, {"name": "Parkside Preschool & Kindergarten", "longlat": ["-122.47625", "37.742615"]}, {"name": "Rooftop (5-8 Mayeda Campus)", "longlat": ["-122.444496", "37.757397"]}, {"name": "Alt School - Potrero Hill", "longlat": ["-122.396584", "37.765507"]}, {"name": "City College of San Francisco Ocean Campus", "longlat": ["-122.451134", "37.725716"]}, {"name": "Little School", "longlat": ["-122.444717", "37.785137"]}, {"name": "Katherine Michiels School", "longlat": ["-122.42231", "37.749817"]}, {"name": "Cross Cultural Family Center - Mary Lane Infant And Toddler Center", "longlat": ["-122.428474", "37.769699"]}, {"name": "Tule Elk Park Early Education School", "longlat": ["-122.434563", "37.799419"]}, {"name": "Kittredge School", "longlat": ["-122.484955", "37.785507"]}, {"name": "Kellys Family Day Care", "longlat": ["-122.427292", "37.741787"]}, {"name": "Serra Preschool", "longlat": ["-122.456116", "37.799297"]}, {"name": "Key", "longlat": ["-122.501999", "37.758099"]}, {"name": "San Francisco Community Alternative School", "longlat": ["-122.432136", "37.726105"]}, {"name": "Ulloa Elementary School", "longlat": ["-122.499397", "37.737316"]}, {"name": "San Francisco Montessori Academy", "longlat": ["-122.490379", "37.757992"]}, {"name": "Town School For Boys", "longlat": ["-122.440132", "37.792034"]}, {"name": "City College of San Francisco Downtown Center", "longlat": ["-122.404724", "37.784565"]}, {"name": "Little Tree Preschool", "longlat": ["-122.419037", "37.746403"]}, {"name": "Marin Day School - Fremont St", "longlat": ["-122.39489", "37.789883"]}, {"name": "Grace Lutheran Church - Grace Infant Care Center", "longlat": ["-122.490852", "37.740261"]}, {"name": "Childrens Day School", "longlat": ["-122.425201", "37.764256"]}, {"name": "Lick-Wilmerding High School", "longlat": ["-122.448982", "37.722321"]}, {"name": "Epiphany Elementary School", "longlat": ["-122.434532", "37.715725"]}, {"name": "Lisa Kampner Hebrew Academy", "longlat": ["-122.42762", "37.767643"]}, {"name": "Montessori School Of The Bay Area", "longlat": ["-122.433311", "37.78159"]}, {"name": "Compass Childrens Center", "longlat": ["-122.413719", "37.782429"]}, {"name": "Cross Cultural Family Center - Turk Street Center", "longlat": ["-122.412865", "37.782799"]}, {"name": "Carver", "longlat": ["-122.385338", "37.731667"]}, {"name": "Saint Luke School (Sls Preschool)", "longlat": ["-122.42234", "37.787209"]}, {"name": "Buen Dia Family School", "longlat": ["-122.423454", "37.761932"]}, {"name": "Preschool", "longlat": ["-122.421791", "37.753262"]}, {"name": "Garfield Elementary / Early Education", "longlat": ["-122.406692", "37.802036"]}, {"name": "City College of San Francisco Evans Center", "longlat": ["-122.384682", "37.741859"]}, {"name": "Presidio Early Education School", "longlat": ["-122.461105", "37.79752"]}, {"name": "Saint John Of San Francisco Orthodox Academy", "longlat": ["-122.486336", "37.780327"]}, {"name": "Live Oak School", "longlat": ["-122.399467", "37.763557"]}, {"name": "Saint James Catholic School", "longlat": ["-122.423592", "37.751137"]}, {"name": "Discovery Center School", "longlat": ["-122.440605", "37.776836"]}, {"name": "Fei Tian Academy Of The Arts California", "longlat": ["-122.453003", "37.770477"]}, {"name": "San Francisco Adventist", "longlat": ["-122.451187", "37.721714"]}, {"name": "One Fifty Parker Ave School", "longlat": ["-122.454094", "37.782818"]}, {"name": "Economic Opportunity Council Sf - Omi Childcare", "longlat": ["-122.465576", "37.714497"]}, {"name": "Calvary Presbyterian Church - Calvary Nursery School", "longlat": ["-122.435089", "37.792713"]}, {"name": "Alt School - Dogpatch 1", "longlat": ["-122.38813", "37.761177"]}, {"name": "Alvarado Elementary School", "longlat": ["-122.438194", "37.753681"]}, {"name": "Mclaren", "longlat": ["-122.423187", "37.713131"]}, {"name": "Cathedral School For Boys", "longlat": ["-122.413414", "37.79229"]}, {"name": "Bright Horizons - Pacific Gas And Electric", "longlat": ["-122.395721", "37.791672"]}, {"name": "Sterne School", "longlat": ["-122.439354", "37.792057"]}, {"name": "Congregation Emanu-El Preschool", "longlat": ["-122.459793", "37.787338"]}, {"name": "City Arts And Tech High School", "longlat": ["-122.424667", "37.718784"]}, {"name": "Saint Thomas More", "longlat": ["-122.473389", "37.712299"]}, {"name": "Independence High School", "longlat": ["-122.463585", "37.763226"]}, {"name": "Cross Cultural Family Center - Richmond I And Ii", "longlat": ["-122.49028", "37.775101"]}, {"name": "Angelinas School Day Care", "longlat": ["-122.5084", "37.77309"]}, {"name": "Convent Of The Sacred Heart High School", "longlat": ["-122.434059", "37.794918"]}, {"name": "Marshall Elementary School", "longlat": ["-122.419022", "37.766289"]}, {"name": "Chinese American International School", "longlat": ["-122.422424", "37.775429"]}, {"name": "Sacred Heart Cathedral Preparatory", "longlat": ["-122.423187", "37.783287"]}, {"name": "Kzv Armenian School - Krouzian Zekarian Armenian School", "longlat": ["-122.478317", "37.713841"]}, {"name": "San Francisco Friends School", "longlat": ["-122.422905", "37.768978"]}, {"name": "Saint John Catholic School", "longlat": ["-122.43753", "37.734886"]}, {"name": "San Francisco School", "longlat": ["-122.411697", "37.732781"]}, {"name": "Cornerstone Academy", "longlat": ["-122.483665", "37.75742"]}, {"name": "Room To Grow Preschool", "longlat": ["-122.424728", "37.73621"]}, {"name": "Grace Cathederal Community Preschool", "longlat": ["-122.413597", "37.792183"]}, {"name": "Youth Chance High School", "longlat": ["-122.392021", "37.792519"]}, {"name": "Nihonmachi Little Friends - After School Program", "longlat": ["-122.428688", "37.786919"]}, {"name": "Presidio Preschool", "longlat": ["-122.460831", "37.782864"]}, {"name": "Crayon Box Preschool", "longlat": ["-122.438774", "37.72329"]}, {"name": "Compass Clara House", "longlat": ["-122.423042", "37.773743"]}, {"name": "Wallenberg", "longlat": ["-122.445953", "37.780647"]}, {"name": "Little Footprints Preschool", "longlat": ["-122.4907", "37.738415"]}, {"name": "Hillwood Academic Day School", "longlat": ["-122.440117", "37.793324"]}, {"name": "ABC Preschool", "longlat": ["-122.493042", "37.781139"]}, {"name": "Saint Thomas The Apostle Elementary School", "longlat": ["-122.499771", "37.775097"]}, {"name": "Fairmount Elementary School / Preschool", "longlat": ["-122.425011", "37.740433"]}, {"name": "Wu Yee Child Development Center - Omi (Ocean View", "longlat": ["-122.47197", "37.717464"]}, {"name": "Yu", "longlat": ["-122.469681", "37.758965"]}, {"name": "Presidio Knolls School", "longlat": ["-122.413704", "37.77319"]}, {"name": "South Of Market Child Care - Judith Baker Child Development Center", "longlat": ["-122.411476", "37.776806"]}, {"name": "Wah Mei School", "longlat": ["-122.477371", "37.76186"]}, {"name": "Stretch The Imagination Child Care Center", "longlat": ["-122.438888", "37.786095"]}, {"name": "C5 Childrens School - Sf City Building Center", "longlat": ["-122.418922", "37.781109"]}, {"name": "Saint Cecilia School", "longlat": ["-122.473602", "37.739872"]}, {"name": "Mission Dolores Academy", "longlat": ["-122.428284", "37.764122"]}, {"name": "Marin Day School - Hills Plaza", "longlat": ["-122.389755", "37.789803"]}, {"name": "Alt School - Alamo Square", "longlat": ["-122.430206", "37.774788"]}, {"name": "Jewish Community High School Of The Bay", "longlat": ["-122.436676", "37.781651"]}, {"name": "South Of Market Child Care - Yerba Buena Gardens Child Development Center", "longlat": ["-122.40081", "37.783512"]}, {"name": "Cow Hollow Kindergarten", "longlat": ["-122.455528", "37.799049"]}, {"name": "Roosevelt", "longlat": ["-122.458351", "37.78228"]}, {"name": "Pacific Primary - Orange Sun School", "longlat": ["-122.441605", "37.775284"]}, {"name": "Gates And Bridges Preschool", "longlat": ["-122.467148", "37.758255"]}, {"name": "Downtown High School", "longlat": ["-122.403702", "37.761398"]}, {"name": "French American International School", "longlat": ["-122.421577", "37.775456"]}, {"name": "Drew", "longlat": ["-122.39389", "37.731796"]}, {"name": "San Francisco International High School", "longlat": ["-122.408859", "37.75523"]}, {"name": "Jefferson Out Of School (OST) Program", "longlat": ["-122.476318", "37.763062"]}, {"name": "Saint James Preschool (Episcopal Church)", "longlat": ["-122.467201", "37.784939"]}, {"name": "Maria Montessori School Of The Golden Gate", "longlat": ["-122.46521", "37.7426"]}, {"name": "Ucsf - Marilyn Reed Lucia Child Care Study Center", "longlat": ["-122.460121", "37.7631"]}, {"name": "King", "longlat": ["-122.399193", "37.753288"]}, {"name": "Jewish Community Center San Francisco - Brotherhood Way Preschool", "longlat": ["-122.475296", "37.713123"]}, {"name": "Kids Kollege Preschool", "longlat": ["-122.505241", "37.756462"]}, {"name": "Lick", "longlat": ["-122.432785", "37.749363"]}, {"name": "Mission Neighborhood Centers - Bernal Dwellings Child Development", "longlat": ["-122.41262", "37.748848"]}, {"name": "El Dorado Elementary School", "longlat": ["-122.407852", "37.718658"]}, {"name": "Alt School - Yerba Buena", "longlat": ["-122.401199", "37.781742"]}, {"name": "True Sunshine Preschool Center", "longlat": ["-122.407844", "37.792976"]}, {"name": "Pomeroy Recreation And Rehabilitation Center", "longlat": ["-122.501846", "37.729641"]}, {"name": "Brightworks", "longlat": ["-122.410377", "37.762238"]}, {"name": "Proof School", "longlat": ["-122.410942", "37.787655"]}, {"name": "Stuart Hall High School", "longlat": ["-122.427238", "37.788628"]}, {"name": "Edison Charter K-8", "longlat": ["-122.426041", "37.754467"]}, {"name": "Mother Goose School", "longlat": ["-122.487839", "37.783024"]}, {"name": "Saint Vincent De Paul School", "longlat": ["-122.437851", "37.796112"]}, {"name": "Our Lady Of The Visitacion School", "longlat": ["-122.409546", "37.709122"]}, {"name": "Gateway Middle School", "longlat": ["-122.435921", "37.779419"]}, {"name": "Cleveland Elementary School", "longlat": ["-122.429192", "37.720341"]}, {"name": "Holy Name Elementary School", "longlat": ["-122.498878", "37.75761"]}, {"name": "Drew School", "longlat": ["-122.442322", "37.787643"]}, {"name": "Asawa", "longlat": ["sawa", "San", "Francisco", "School", "Of", "The", "Art"]}, {"name": "\n", "longlat": []}, {"name": " / Academy Of Arts And Sciences", "longlat": ["-122.44883", "37.745316"]}, {"name": "Kai Ming Head Start - Saint Luke Center", "longlat": ["-122.42215", "37.792061"]}, {"name": "Peekadoodle Of San Francisco", "longlat": ["-122.423187", "37.805534"]}, {"name": "Glen Park Montessori Preschool", "longlat": ["-122.432915", "37.734295"]}, {"name": "Stratford School - San Francisco", "longlat": ["-122.461632", "37.723126"]}, {"name": "Wu Yee Child Development Center - Bayview", "longlat": ["-122.38958", "37.731804"]}, {"name": "Wu Yee Child Development Center - South East", "longlat": ["-122.393837", "37.737419"]}, {"name": "Economic Opportunity Council Sf - Chinatown Childcare", "longlat": ["-122.41523", "37.803215"]}, {"name": "Lone Mountain Childrens Center", "longlat": ["-122.473633", "37.788681"]}, {"name": "My City School", "longlat": ["-122.438148", "37.764423"]}, {"name": "Sunnyside Elementary School", "longlat": ["-122.448257", "37.730293"]}, {"name": "Economic Opportunity Council Sf - Cleo Wallace Childcare", "longlat": ["-122.394699", "37.755669"]}, {"name": "Little People Preschool ", "longlat": ["-122.504295", "37.741543"]}, {"name": "Mercy High School", "longlat": ["-122.473587", "37.7295"]}, {"name": "Saint Anne Elementary School", "longlat": ["-122.471283", "37.763023"]}, {"name": "Zion Lutheran School", "longlat": ["-122.467636", "37.77924"]}, {"name": "Our Victorian Schoolhouse", "longlat": ["-122.438637", "37.777241"]}, {"name": "Nihonmachi Little Friends - Bush St", "longlat": ["-122.430588", "37.78709"]}, {"name": "Revere", "longlat": ["-122.413116", "37.737614"]}, {"name": "Meadows-Livingstone School", "longlat": ["-122.404839", "37.749626"]}, {"name": "City College of San Francisco Chinatown North Beach Center", "longlat": ["-122.404701", "37.795555"]}, {"name": "Aptos Middle School", "longlat": ["-122.465782", "37.729672"]}, {"name": "Good Samaritan Child Development Center", "longlat": ["-122.40657", "37.751873"]}, {"name": "Lilienthal", "longlat": ["-122.458015", "37.787201"]}, {"name": "Archbishop Riordan High School", "longlat": ["-122.453056", "37.727902"]}, {"name": "Martha Hills Learning Center", "longlat": ["-122.394241", "37.719162"]}, {"name": "Sunset Elementary School", "longlat": ["-122.499153", "37.750523"]}, {"name": "Wu Yee Child Development Center - New Generation", "longlat": ["-122.418098", "37.710182"]}, {"name": "Presidio Middle School", "longlat": ["-122.489624", "37.780865"]}, {"name": "Bright Horizons - 2Nd St", "longlat": ["-122.395569", "37.785294"]}, {"name": "Buena Vista Child Care", "longlat": ["-122.42028", "37.753567"]}, {"name": "Wu Yee Child Development Center - Generations", "longlat": ["-122.403709", "37.798492"]}, {"name": "Mission Neighborhood Centers - Southeast Families United Childcare", "longlat": ["-122.383591", "37.739754"]}, {"name": "Wu Yee Child Development Center - Hunters Point/Kirkwood", "longlat": ["-122.374405", "37.72887"]}, {"name": "Mission Neighborhood Centers - Mission Bay", "longlat": ["-122.39299", "37.776493"]}, {"name": "Tenderloin Elementary / Early Education", "longlat": ["-122.419777", "37.781796"]}, {"name": "Bay School Of San Francisco", "longlat": ["-122.455818", "37.800579"]}, {"name": "Lakeside Presbyterian Center For Children", "longlat": ["-122.475197", "37.730774"]}, {"name": "Chinese Education Center Elementary School", "longlat": ["-122.40406", "37.794769"]}, {"name": "Mahler", "longlat": ["-122.428093", "37.755276"]}, {"name": "Saint Philip School", "longlat": ["-122.435539", "37.751759"]}, {"name": "San Francisco Day School", "longlat": ["-122.446281", "37.778042"]}, {"name": "Denman", "longlat": ["-122.443184", "37.72131"]}, {"name": "Saint Brigid School", "longlat": ["-122.424759", "37.795147"]}, {"name": "Harte", "longlat": ["-122.389221", "37.717899"]}, {"name": "Rise Institute", "longlat": ["-122.394058", "37.750324"]}, {"name": "Learning Bridge Preschool", "longlat": ["-122.472206", "37.760243"]}, {"name": "Larkin Street Youth Services Academy", "longlat": ["-122.412987", "37.782265"]}, {"name": "Alt School - Dogpatch 2", "longlat": ["-122.387962", "37.760662"]}, {"name": "Immaculate Conception Academy", "longlat": ["-122.423416", "37.751667"]}, {"name": "C5 Childrens School - State Building Center", "longlat": ["-122.417915", "37.78104"]}, {"name": "Lowell High School", "longlat": ["-122.483055", "37.729435"]}, {"name": "Alt School - North Beach", "longlat": ["-122.404892", "37.795811"]}, {"name": "Wu Yee Child Development Center - Cadillac", "longlat": ["-122.41394", "37.784054"]}, {"name": "Lilienthal", "longlat": ["-122.443237", "37.80336"]}, {"name": "Lafayette Elementary School", "longlat": ["-122.496887", "37.777069"]}, {"name": "Woodside International School", "longlat": ["-122.474747", "37.763432"]}, {"name": "Faces Sf Child Development Program - Haight Ashbury/Masonic", "longlat": ["-122.445869", "37.770889"]}, {"name": "Mission Neighborhood Centers - Capp Head Start", "longlat": ["-122.418495", "37.760986"]}, {"name": "Mission Neighborhood Centers - Jean Jacobs", "longlat": ["-122.429695", "37.720951"]}, {"name": "Jordan", "longlat": ["-122.425148", "37.719536"]}, {"name": "City College of San Francisco Gough Street Location", "longlat": ["-122.421211", "37.771988"]}, {"name": "Muir", "longlat": ["-122.42868", "37.773758"]}, {"name": "O'Connell", "longlat": ["-122.413559", "37.759514"]}, {"name": "Saint Charles School", "longlat": ["-122.416443", "37.762322"]}, {"name": "Friends Of Potrero Hill Preschool", "longlat": ["-122.389587", "37.75856"]}, {"name": "Parks", "longlat": ["-122.429504", "37.783009"]}, {"name": "Angelinas Preschool", "longlat": ["-122.483765", "37.753666"]}, {"name": "Wu Yee Child Development Center - Golden Gate", "longlat": ["-122.413559", "37.78167"]}, {"name": "Brown", "longlat": ["-122.399574", "37.736477"]}, {"name": "Chavez", "longlat": ["-122.414879", "37.754921"]}, {"name": "Feinstein", "longlat": ["-122.481369", "37.739685"]}, {"name": "Monroe Elementary / Excelsior Monroe Early Education", "longlat": ["-122.430489", "37.725399"]}, {"name": "Alt School - Soma", "longlat": ["-122.410484", "37.774181"]}, {"name": "Chinese Immersion School At Deavila", "longlat": ["-122.444275", "37.769829"]}, {"name": "Living Hope Christian School", "longlat": ["-122.435829", "37.714336"]}, {"name": "Happy Times Nursery School", "longlat": ["-122.476791", "37.748856"]}, {"name": "Voice Of Pentecost Academy", "longlat": ["-122.463974", "37.726364"]}, {"name": "San Miguel Early Education School", "longlat": ["-122.44471", "37.721645"]}, {"name": "Ucsf - University Child Care Center - Mission Bay", "longlat": ["-122.393967", "37.768677"]}, {"name": "Longfellow Elementary School", "longlat": ["-122.446739", "37.710423"]}, {"name": "Webster", "longlat": ["-122.395843", "37.760521"]}, {"name": "Mission High School", "longlat": ["-122.427307", "37.76202"]}, {"name": "Miraloma Elementary School", "longlat": ["-122.450188", "37.738636"]}, {"name": "Golden Gate Guppies Preschool", "longlat": ["-122.434509", "37.789124"]}, {"name": "Lands End School", "longlat": ["-122.504578", "37.782593"]}, {"name": "San Francisco Pacific Academy", "longlat": ["-122.494286", "37.775639"]}, {"name": "Wells", "longlat": ["-122.433899", "37.775013"]}, {"name": "Munchkinland Preschool And Family Daycare", "longlat": ["-122.509254", "37.773445"]}]